LICENSE
README.md
setup.py
blogsmith/__init__.py
blogsmith/blogger.py
blogsmith/requirements.txt
blogsmith.egg-info/PKG-INFO
blogsmith.egg-info/SOURCES.txt
blogsmith.egg-info/dependency_links.txt
blogsmith.egg-info/not-zip-safe
blogsmith.egg-info/requires.txt
blogsmith.egg-info/top_level.txt