Metadata-Version: 2.1
Name: blogsmith
Version: 1.1.6
Summary: Automatic LLM-based multi-agent blog builder
Home-page: https://github.com/ptarau/blogsmith.git
Author: Paul Tarau
Author-email: ptarau@gmail.com
License: MIT
License-File: LICENSE
